[
  {
    "id": "gateau-de-mamie",
    "title": "Les gâteaux de mamie",
    "image": "/images/pizza-royale.jpeg",
    "category": "DESSERT",
    "tags":[],
    "family": "BOUVIER",
    "recap-sheet": "/Recettes_pages/...",
    "ingredients-lists": [
      {
        "title": "Pour la pâte feuilletée",
        "ingredients": [
          "3 oeufs", "Farine"
        ]
      },
      {
        "title": "Pour la sauce tomate",
        "ingredients": [
          "3 tomates", "Sel"
        ]
      }
    ],
    "quantite": "9 personnes",
    "steps": [
      {
        "image": "/images/pizza-royale.jpeg",
        "video": "",
        "text": ""
      },
      {
        "image": "/images/pizza-royale.jpeg",
        "video": "",
        "text": ""
      }
    ],
    "chef_word": "Mot du chef personnalisé",
    "videos": [
      {
        "title": "",
        "src": "/videos/"
      }
    ]
  },
  {
    "id": "ragout-de-pommes-de-terre",
    "title": "Ragout de pomme de terre",
    "image": "/images/pizza-royale.jpeg",
    "category": "PLAT_PRINCIPAL",
    "tags":[],
    "family": "BOUVIER",
    "recap-sheet": "/Recettes_pages/...",
    "ingredients-lists": [
      {
        "title": "",
        "ingredients": [
          "3 oeufs", "Farine"
        ]
      }
    ],
    "quantite": "",
    "steps": [
      {
        "image": "",
        "video": "",
        "text": ""
      },
      {
        "image": "/images/pizza-royale.jpeg",
        "video": "",
        "text": ""
      }
    ],
    "chef_word": "Mot du chef personnalisé",
    "videos": [
      {
        "title": "",
        "src": "/videos/"
      }
    ]
  }
]
